cpu_load_generator/__init__.py
cpu_load_generator/__main__.py
cpu_load_generator/_interface.py
cpu_load_generator/common/__init__.py
cpu_load_generator/common/_closed_loop_actuator.py
cpu_load_generator/common/_controller.py
cpu_load_generator/common/_monitor.py
cpu_load_generator-1.2.0.dist-info/LICENCE
cpu_load_generator-1.2.0.dist-info/METADATA
cpu_load_generator-1.2.0.dist-info/WHEEL
cpu_load_generator-1.2.0.dist-info/top_level.txt
cpu_load_generator-1.2.0.dist-info/RECORD
