Metadata-Version: 2.1
Name: cpu-load-generator
Version: 1.2.0
Summary: CPU load generator
Home-page: https://github.com/sirtyman/CPULoadGenerator
Author: Marcin Tyman
Author-email: marcin.tyman@gmail.com
License: MIT
Platform: UNKNOWN
Classifier: License :: OSI Approved :: MIT License
Classifier: Programming Language :: Python :: 3
Requires-Dist: psutil
